spn.py
spn-0.2.2.dist-info/entry_points.txt
spn-0.2.2.dist-info/LICENSE
spn-0.2.2.dist-info/WHEEL
spn-0.2.2.dist-info/METADATA
spn-0.2.2.dist-info/RECORD
