Metadata-Version: 2.1
Name: spn
Version: 0.2.2
Summary: Unofficial CLI for the Wayback Machine's Save Page Now API.
Author-email: Chris Coleman <chris@chriscoleman.uk>
Classifier: License :: OSI Approved :: MIT License
Requires-Dist: click
Requires-Dist: confuse
Requires-Dist: httpx
Requires-Dist: jsonlines
Requires-Dist: tenacity
